treenodedefinition.py
treenodedefinition-0.1.dist-info/LICENSE
treenodedefinition-0.1.dist-info/METADATA
treenodedefinition-0.1.dist-info/WHEEL
treenodedefinition-0.1.dist-info/top_level.txt
treenodedefinition-0.1.dist-info/RECORD
