Metadata-Version: 2.1
Name: treenodedefinition
Version: 0.1
Summary: Helper functions to make fitting outputs for doctests.
Home-page: https://gitlab.com/david.scheliga/treenodedefinition
Author: David Scheliga
License: GNU General Public License V3 (GPLv3)
Project-URL: Source Code Repository, https://gitlab.com/david.scheliga/treenodedefinition
Keywords: doctest,helper,pandas
Platform: UNKNOWN
Classifier: Development Status :: 5 - Production/Stable
Classifier: License :: OSI Approved :: GNU General Public License v3 (GPLv3)
Classifier: Operating System :: OS Independent
Classifier: Programming Language :: Python
Classifier: Programming Language :: Python :: 3.6
Classifier: Programming Language :: Python :: 3.7
Classifier: Programming Language :: Python :: 3.8
Classifier: Programming Language :: Python :: 3.9
License-File: LICENSE
